pushno/__init__.py
pushno/exceptions.py
pushno/pushno.py
pushno/consts/__init__.py
pushno/consts/prowlconsts.py
pushno/consts/pushoverconsts.py
pushno/messages/__init__.py
pushno/messages/basemessage.py
pushno/messages/prowlmessages.py
pushno/messages/pushovermessages.py
pushno/plugins/__init__.py
pushno/plugins/baseplugin.py
pushno/plugins/prowl.py
pushno/plugins/pushover.py
pushno/schemas/__init__.py
pushno/schemas/prowlschema.py
pushno/schemas/pushoverschema.py
pushno-0.0.3.dist-info/LICENSE.txt
pushno-0.0.3.dist-info/METADATA
pushno-0.0.3.dist-info/WHEEL
pushno-0.0.3.dist-info/top_level.txt
pushno-0.0.3.dist-info/RECORD
