Metadata-Version: 2.1
Name: pushno
Version: 0.0.3
Summary: Push Notifications
Home-page: https://github.com/keans/pushno
Author: Ansgar Kellner
Author-email: keans@gmx.de
License: MIT
Keywords: python packaging
Platform: UNKNOWN
Classifier: Development Status :: 3 - Alpha
Classifier: Intended Audience :: Developers
Classifier: Topic :: Software Development :: Build Tools
Classifier: License :: OSI Approved :: MIT License
Classifier: Programming Language :: Python :: 3
Classifier: Programming Language :: Python :: 3.6
Classifier: Programming Language :: Python :: 3.7
Classifier: Programming Language :: Python :: 3.8
Classifier: Programming Language :: Python :: 3.9
Classifier: Programming Language :: Python :: 3.10
Requires-Dist: requests
Requires-Dist: cerberus
